mask4llm/__init__.py
mask4llm/app.py
mask4llm/masking.py
mask4llm/session.py
mask4llm/styles.tcss
mask4llm/tui.py
mask4llm/util.py
mask4llm/widgets/copy_on_enter_log.py
mask4llm-1.0.0.dist-info/METADATA
mask4llm-1.0.0.dist-info/WHEEL
mask4llm-1.0.0.dist-info/entry_points.txt
mask4llm-1.0.0.dist-info/licenses/LICENSE
mask4llm-1.0.0.dist-info/RECORD
