Metadata-Version: 2.4
Name: mask4llm
Version: 1.0.0
Summary: A terminal user interface (TUI) app built with Textual to easily mask and unmask sensitive information.
Author-email: Hemanth Kumar <hemanthhari2000@gmail.com>
License: MIT
License-File: LICENSE
Keywords: TUI,Textual,masking,privacy,unmasking
Classifier: Environment :: Console
Classifier: Environment :: Console :: Curses
Classifier: Intended Audience :: Developers
Classifier: Intended Audience :: End Users/Desktop
Classifier: Intended Audience :: Information Technology
Classifier: License :: OSI Approved :: MIT License
Classifier: Natural Language :: English
Classifier: Operating System :: OS Independent
Classifier: Programming Language :: Python :: 3
Classifier: Programming Language :: Python :: 3.12
Classifier: Topic :: Software Development :: Libraries :: Application Frameworks
Classifier: Topic :: Utilities
Requires-Python: >=3.12
Requires-Dist: pyperclip>=1.9.0
Requires-Dist: textual[syntax]>=3.7.1
